{"is_source_file": true, "format": "TypeScript", "description": "An Angular component defining the 'DashboardComponent' for the dashboard page, including template HTML with UI elements like icons, badges, buttons, and styled sections.", "external_files": ["../../../../projects/ui-kit/src/lib/atoms/ui-button/ui-button.component", "../../../../projects/ui-kit/src/lib/atoms/ui-icon/ui-icon.component", "../../../../projects/ui-kit/src/lib/atoms/ui-badge/ui-badge.component"], "external_methods": [], "published": ["DashboardComponent"], "classes": [{"name": "DashboardComponent", "description": "Angular component representing the dashboard page with a UI layout for displaying metrics and controls."}], "methods": [], "calls": [], "search-terms": ["DashboardComponent", "Angular", "dashboard.page.ts", "UI elements", "template HTML", "standalone component", "UI kit"], "state": 2, "file_id": 51, "knowledge_revision": 163, "git_revision": "3b08c760ea2c4b94e68359be6acd6966222aa3eb", "revision_history": [{"142": ""}, {"145": ""}, {"146": ""}, {"147": ""}, {"148": ""}, {"154": "3b08c760ea2c4b94e68359be6acd6966222aa3eb"}, {"156": "3b08c760ea2c4b94e68359be6acd6966222aa3eb"}, {"163": "3b08c760ea2c4b94e68359be6acd6966222aa3eb"}], "ctags": [{"_type": "tag", "name": "DashboardComponent", "path": "/home/kavia/workspace/code-generation/elegant-dashboard-platform-2609-2619/angular_frontend/src/app/pages/dashboard/dashboard.component.ts", "pattern": "/^export class DashboardComponent {}$/", "language": "TypeScript", "kind": "class"}], "hash": "3e4106bbcc55cd9dd2a647ff9b0c8090", "format-version": 4, "code-base-name": "angular_frontend", "filename": "angular_frontend/src/app/pages/dashboard/dashboard.component.ts"}